psr/apps/__init__.py
psr/apps/apps.py
psr/apps/version.py
psr/execqueue/client.py
psr/execqueue/config.py
psr/execqueue/db.py
psr/execqueue/server.py
psr/execqueue/watcher.py
psr/factory/__init__.py
psr/factory/api.py
psr/factory/factory.dll
psr/factory/factory.pmd
psr/factory/factory.pmk
psr/factory/factorylib.py
psr/factory/libcurl-x64.dll
psr/factory/py.typed
psr/factory/samples/__init__.py
psr/factory/samples/sddp_case01.py
psr/factory/samples/sddp_case21.py
psr/outputs/__init__.py
psr/outputs/outputs.py
psr/outputs/resample.py
psr/psrfcommon/__init__.py
psr/psrfcommon/psrfcommon.py
psr/psrfcommon/tempfile.py
psr/runner/__init__.py
psr/runner/runner.py
psr/runner/version.py
psr_factory-5.0.0b77.dist-info/licenses/LICENSE.txt
psr_factory-5.0.0b77.dist-info/METADATA
psr_factory-5.0.0b77.dist-info/WHEEL
psr_factory-5.0.0b77.dist-info/top_level.txt
psr_factory-5.0.0b77.dist-info/RECORD
