Metadata-Version: 2.4
Name: psr-factory
Version: 5.0.0b77
Summary: PSR database management module.
Author-email: "PSR Inc." <psrfactory@psr-inc.com>
License-Expression: MIT
Project-URL: documentation, https://docs.psr-inc.com/factory/
Keywords: psr,factory,sddp
Classifier: Development Status :: 4 - Beta
Classifier: Programming Language :: C
Classifier: Programming Language :: C++
Classifier: Programming Language :: Python :: 3
Classifier: Programming Language :: Python :: 3.9
Classifier: Programming Language :: Python :: 3.10
Classifier: Programming Language :: Python :: 3.11
Classifier: Programming Language :: Python :: 3.12
Classifier: Programming Language :: Python :: 3.13
Classifier: Programming Language :: Python :: 3.14
Classifier: Topic :: Software Development
Classifier: Topic :: Scientific/Engineering
Classifier: Operating System :: Microsoft :: Windows
Classifier: Operating System :: POSIX :: Linux
Requires-Python: >=3.9
License-File: LICENSE.txt
Requires-Dist: numpy
Provides-Extra: pandas
Requires-Dist: pandas; extra == "pandas"
Provides-Extra: polars
Requires-Dist: polars; extra == "polars"
Provides-Extra: cloud
Requires-Dist: psr-cloud; extra == "cloud"
Provides-Extra: execqueue-client
Requires-Dist: requests; extra == "execqueue-client"
Provides-Extra: execqueue-server
Requires-Dist: DateTime; extra == "execqueue-server"
Requires-Dist: Flask; extra == "execqueue-server"
Requires-Dist: python-ulid; extra == "execqueue-server"
Requires-Dist: sqlalchemy; extra == "execqueue-server"
Requires-Dist: python-dotenv; extra == "execqueue-server"
Requires-Dist: psr-cloud; extra == "execqueue-server"
Provides-Extra: all
Requires-Dist: pandas; extra == "all"
Requires-Dist: polars; extra == "all"
Requires-Dist: psutil; extra == "all"
Requires-Dist: psr-cloud; extra == "all"
Dynamic: license-file
